rethit_auto_package/__init__.py
rethit_auto_package/main.py
rethit_auto_package-0.2.0.dist-info/licenses/LICENSE
rethit_auto_package-0.2.0.dist-info/METADATA
rethit_auto_package-0.2.0.dist-info/WHEEL
rethit_auto_package-0.2.0.dist-info/entry_points.txt
rethit_auto_package-0.2.0.dist-info/top_level.txt
rethit_auto_package-0.2.0.dist-info/RECORD
